{
  "id": "OPM-2025-0004-1845",
  "title": "Comment from Walter Richardson",
  "category": "Agency",
  "analysis": {
    "stance": "Against",
    "themes": [
      "Due process/employee rights",
      "Institutional knowledge loss"
    ],
    "key_quote": "Civil service employees should have the opportunity for due process if accused of poor performance or malfeasance and should not be fired at will.",
    "rationale": "The comment explicitly opposes the proposed rule by emphasizing the importance of due process and the risks associated with losing experienced staff, which aligns with concerns about the politicization of civil service."
  },
  "occurrence_number": 0,
  "duplicate_of": ""
}