{
  "id": "OPM-2025-0004-18134",
  "title": "Comment from Anonymous",
  "category": "Agency",
  "analysis": {
    "stance": "Against",
    "themes": [
      "Politicization concerns",
      "Scientific integrity"
    ],
    "key_quote": "These should be free of politicization.",
    "rationale": "The comment explicitly opposes the proposed rule by highlighting concerns about politicization in the appointment of directors at NIH, which aligns with the themes of maintaining scientific integrity and nonpartisan governance."
  },
  "occurrence_number": 1,
  "duplicate_of": ""
}