{
  "id": "OPM-2025-0004-20167",
  "title": "Comment from Anonymous",
  "category": "",
  "analysis": {
    "stance": "Against",
    "themes": [
      "Politicization concerns",
      "Scientific integrity"
    ],
    "key_quote": "Schedule F could make all Institute and Center Directors and division directors political appointees. This would politicize NIH, compromising scientific identity and the very principles upon which NIH is founded.",
    "rationale": "The comment expresses strong opposition to Schedule F by highlighting concerns about the potential politicization of scientific positions and the integrity of federal grants, which aligns with the themes of politicization and scientific integrity."
  },
  "occurrence_number": 0,
  "duplicate_of": ""
}