{
  "id": "OPM-2025-0004-14296",
  "title": "Comment from Molly Schreiner",
  "category": "Agency",
  "analysis": {
    "stance": "Against",
    "themes": [
      "Merit-based system concerns",
      "Due process/employee rights",
      "Politicization concerns"
    ],
    "key_quote": "A country is only as strong as its civil service.",
    "rationale": "The comment expresses concerns about the negative impact of the proposed rule on the federal service's ability to function effectively and emphasizes the importance of a strong, nonpartisan civil service, which opposes the politicization implied by the rule."
  },
  "occurrence_number": 0,
  "duplicate_of": ""
}