{
  "id": "OPM-2025-0004-1418",
  "title": "Comment from Jessica Windham",
  "category": "Agency",
  "analysis": {
    "stance": "Against",
    "themes": [
      "Merit-based system concerns",
      "Due process/employee rights",
      "Politicization concerns"
    ],
    "key_quote": "The work they did was political and their ability to serve shouldn\u2019t be subject to political whims.",
    "rationale": "The comment explicitly opposes the reclassification of workers to make them easier to fire, highlighting concerns about politicization and the impact on workers' rights and representation."
  },
  "occurrence_number": 0,
  "duplicate_of": ""
}