{
  "id": "OPM-2025-0004-17370",
  "title": "Comment from Nissan Lew",
  "category": "Agency",
  "analysis": {
    "stance": "Against",
    "themes": [
      "Politicization concerns"
    ],
    "key_quote": "DO NOT PUT POLITICS INTO CIVIL SERVICE!",
    "rationale": "The comment explicitly opposes the implementation of Schedule F, emphasizing the importance of keeping politics out of civil service, which aligns with concerns about politicization."
  },
  "occurrence_number": 1,
  "duplicate_of": ""
}