{
  "id": "OPM-2025-0004-16256",
  "title": "Comment from Anonymous",
  "category": "Citizen",
  "analysis": {
    "stance": "Against",
    "themes": [
      "Merit-based system concerns",
      "Due process/employee rights",
      "Politicization concerns"
    ],
    "key_quote": "Absolutely not. Considering how many hard working federal employees they've already tried to fire without warning or cause, it's obvious the only party for which there needs to be accountability in this matter is OPM itself.",
    "rationale": "The comment expresses strong opposition to the proposed rule by highlighting concerns about the treatment of federal employees and the need for accountability within OPM, indicating a defense of existing protections and oversight mechanisms."
  },
  "occurrence_number": 0,
  "duplicate_of": ""
}