{
  "id": "OPM-2025-0004-9437",
  "title": "Comment from Anonymous",
  "category": "Professional Organization",
  "analysis": {
    "stance": "Against",
    "themes": [
      "Due process/employee rights",
      "Politicization concerns",
      "Merit-based system concerns"
    ],
    "key_quote": "I adamantly object to reviving the Schedule F classification for federal workers.",
    "rationale": "The comment explicitly opposes the revival of Schedule F, citing concerns about due process rights and the non-partisan nature of civil service, which indicates a strong opposition to the proposed rule."
  },
  "occurrence_number": 0,
  "duplicate_of": ""
}