{
  "id": "OPM-2025-0004-11636",
  "title": "Comment from Anonymous",
  "category": "Citizen",
  "analysis": {
    "stance": "Against",
    "themes": [
      "Merit-based system concerns",
      "Due process/employee rights",
      "Politicization concerns",
      "Institutional knowledge loss"
    ],
    "key_quote": "The proposed rule prioritizes loyalty over competence.",
    "rationale": "The comment explicitly opposes the proposed rule, highlighting concerns about prioritizing loyalty over competence and the potential for increased fraud and waste, which aligns with themes of merit-based systems and politicization."
  },
  "occurrence_number": 0,
  "duplicate_of": ""
}