{
  "id": "OPM-2025-0004-2999",
  "title": "Comment from Julie Fitzgerald",
  "category": "Citizen",
  "analysis": {
    "stance": "Against",
    "themes": [
      "Politicization concerns"
    ],
    "key_quote": "this change would lessen the ability of agencies and organizations to maintain impartiality and to uphold the rule of law and the Constitution no matter who is occupying the White House at any given time.",
    "rationale": "The comment explicitly opposes the proposed rule by expressing concerns about impartiality and the rule of law, which are critical indicators of opposition to the politicization of civil service."
  },
  "occurrence_number": 1,
  "duplicate_of": ""
}