{
  "id": "OPM-2025-0004-4728",
  "title": "Comment from Anonymous",
  "category": "",
  "analysis": {
    "stance": "Against",
    "themes": [
      "Politicization concerns"
    ],
    "key_quote": "Federal employees are not pawns. They are public servants. This should not pass.",
    "rationale": "The comment expresses opposition to the proposed rule by emphasizing the role of federal employees as public servants and warning against the politicization of their positions, indicating a concern about setting a dangerous precedent."
  },
  "occurrence_number": 1,
  "duplicate_of": ""
}