{
  "id": "OPM-2025-0004-12014",
  "title": "Comment from Dorothy McQuown",
  "category": "Citizen",
  "analysis": {
    "stance": "Against",
    "themes": [
      "Politicization concerns"
    ],
    "key_quote": "Any effort to politicize government jobs at all levels is undemocratic and against American principles.",
    "rationale": "The comment explicitly opposes the politicization of government jobs, framing it as undemocratic and contrary to American principles, which aligns with concerns about the proposed rule."
  },
  "occurrence_number": 1,
  "duplicate_of": ""
}