{
  "id": "OPM-2025-0004-6575",
  "title": "Comment from Christina Werner",
  "category": "",
  "analysis": {
    "stance": "Against",
    "themes": [
      "Politicization concerns",
      "Scientific integrity"
    ],
    "key_quote": "If political views, rather than scientific expertise, drive decision-making, this is not possible.",
    "rationale": "The comment opposes the proposed changes by emphasizing the need for scientific independence and the dangers of politicization in decision-making, which aligns with concerns about the integrity of federally supported science."
  },
  "occurrence_number": 0,
  "duplicate_of": ""
}