{
  "id": "OPM-2025-0004-12646",
  "title": "Comment from Mary Cronin",
  "category": "Agency",
  "analysis": {
    "stance": "Against",
    "themes": [
      "Merit-based system concerns",
      "Due process/employee rights",
      "Politicization concerns"
    ],
    "key_quote": "I am strongly opposed to the proposed reinstatement of Schedule F. Our federal civil service employees should be chosen only by qualifications and merit - the education and skills or the applicant or holder of career positions.",
    "rationale": "The comment explicitly opposes the reinstatement of Schedule F, emphasizing the importance of merit-based hiring and the dangers of politicization in civil service, which aligns with concerns about due process and employee rights."
  },
  "occurrence_number": 0,
  "duplicate_of": ""
}