{
  "id": "OPM-2025-0004-14669",
  "title": "Comment from Anna Brown",
  "category": "Citizen",
  "analysis": {
    "stance": "Against",
    "themes": [
      "Merit-based system concerns",
      "Due process/employee rights",
      "Politicization concerns",
      "Scientific integrity",
      "Institutional knowledge loss"
    ],
    "key_quote": "By making political loyalty more important than expertise in federal employment, this rule would destabilize essential services such as Social Security, Medicare, Medicaid, national security, and others.",
    "rationale": "The comment strongly opposes the proposed rule by highlighting concerns about politicization, the importance of expertise over political loyalty, and the potential negative impacts on federal services and scientific integrity."
  },
  "occurrence_number": 0,
  "duplicate_of": ""
}