{
  "id": "OPM-2025-0004-12901",
  "title": "Comment from Anonymous",
  "category": "Citizen",
  "analysis": {
    "stance": "Against",
    "themes": [
      "Merit-based system concerns",
      "Due process/employee rights",
      "Politicization concerns",
      "Scientific integrity"
    ],
    "key_quote": "Instituting policies that allow for the at-will removal of federal employees\u2014especially scientists\u2014threatens the integrity of public service and scientific research.",
    "rationale": "The comment explicitly opposes the proposed rule, highlighting concerns about the integrity of public service, the potential for political retaliation, and the negative impact on recruitment and retention of talented professionals. These points align with themes of merit-based systems, due process, and politicization."
  },
  "occurrence_number": 0,
  "duplicate_of": ""
}