{
  "id": "OPM-2025-0004-5512",
  "title": "Comment from Katy Dunn",
  "category": "Citizen",
  "analysis": {
    "stance": "Against",
    "themes": [
      "Merit-based system concerns",
      "Politicization concerns"
    ],
    "key_quote": "The public sees these \"loyalty tests\" and understands the effort to bend the entire Federal government to the whims of a sitting administration.",
    "rationale": "The comment opposes the proposed rule by emphasizing the importance of expertise over political loyalty in hiring and firing civil servants, highlighting concerns about politicization and the potential harm to public trust and government effectiveness."
  },
  "occurrence_number": 1,
  "duplicate_of": ""
}