{
  "id": "OPM-2025-0004-11334",
  "title": "Comment from David Neuendorff",
  "category": "Professional Organization",
  "analysis": {
    "stance": "Against",
    "themes": [
      "Merit-based system concerns",
      "Due process/employee rights",
      "Politicization concerns"
    ],
    "key_quote": "Protect current government employees and value their dedication and professionalism.",
    "rationale": "The comment expresses a clear opposition to the proposed rule by emphasizing the importance of protecting government employees and valuing their professionalism, which aligns with concerns about maintaining a merit-based system and preventing corruption and politicization."
  },
  "occurrence_number": 1,
  "duplicate_of": ""
}