{
  "id": "OPM-2025-0004-12679",
  "title": "Comment from Anonymous",
  "category": "",
  "analysis": {
    "stance": "Against",
    "themes": [
      "Politicization concerns"
    ],
    "key_quote": "I oppose this rule because it would enable the president to censor and control the federal workforce to a degree that is unconstitutional and unAmerican.",
    "rationale": "The comment explicitly opposes the rule by highlighting concerns about presidential overreach and its implications for democratic governance, which aligns with themes of politicization."
  },
  "occurrence_number": 1,
  "duplicate_of": ""
}