{
  "id": "OPM-2025-0004-9566",
  "title": "Comment from Marla Dial",
  "category": "Professional Organization",
  "analysis": {
    "stance": "Against",
    "themes": [
      "Merit-based system concerns",
      "Due process/employee rights",
      "Politicization concerns",
      "Scientific integrity"
    ],
    "key_quote": "The proposed Schedule F rule should be rejected because it is antithetical to democracy.",
    "rationale": "The comment strongly opposes the proposed Schedule F rule, highlighting concerns about politicization, the undermining of democracy, and the potential negative impact on public service integrity and scientific expertise."
  },
  "occurrence_number": 0,
  "duplicate_of": ""
}