{
  "id": "OPM-2025-0004-0974",
  "title": "Comment from Libby Overly",
  "category": "Agency",
  "analysis": {
    "stance": "Against",
    "themes": [
      "Merit-based system concerns",
      "Due process/employee rights",
      "Politicization concerns",
      "Institutional knowledge loss"
    ],
    "key_quote": "Reinstating Schedule F would be a disaster. People who work in government are there to serve the people.",
    "rationale": "The comment explicitly opposes the proposed rule, highlighting concerns about the loss of institutional knowledge and the potential for politicization of civil service. It also criticizes the motivations behind the rule, indicating a strong defense of merit-based systems and employee rights."
  },
  "occurrence_number": 0,
  "duplicate_of": ""
}