{
  "id": "OPM-2025-0004-1149",
  "title": "Comment from Lauren Austrian-Parke",
  "category": "Citizen",
  "analysis": {
    "stance": "Against",
    "themes": [
      "Merit-based system concerns",
      "Due process/employee rights",
      "Politicization concerns"
    ],
    "key_quote": "I want these positions protected from the increased politicization and partisanship in our country; I value government employees\u2019 experience and skill at their jobs over their ability to follow a President\u2019s agenda.",
    "rationale": "The comment explicitly opposes the rule by emphasizing the need for civil service protections and expressing concerns about politicization and partisanship, particularly in the context of the current administration's actions."
  },
  "occurrence_number": 0,
  "duplicate_of": ""
}