{
  "id": "OPM-2025-0004-8135",
  "title": "Comment from Anonymous",
  "category": "Citizen",
  "analysis": {
    "stance": "For",
    "themes": [
      "Politicization concerns"
    ],
    "key_quote": "So the problem this rule is aimed at is real and I get why Trump wants it.",
    "rationale": "The comment explicitly supports the rule by acknowledging the issue of federal employees resisting policies they disagree with and expressing understanding of the need for the proposed changes to hold employees accountable."
  },
  "occurrence_number": 0,
  "duplicate_of": ""
}