{
  "id": "OPM-2025-0004-4005",
  "title": "Comment from Suru Way",
  "category": "Professional Organization",
  "analysis": {
    "stance": "Against",
    "themes": [
      "Merit-based system concerns"
    ],
    "key_quote": "Federal jobs should be reserved for individuals who are capable, qualified, and committed to serving the public effectively.",
    "rationale": "The comment emphasizes the importance of merit and qualifications in federal employment, which aligns with concerns about maintaining a merit-based system. It indirectly opposes the proposed rule by advocating for competency and professionalism rather than politicization."
  },
  "occurrence_number": 0,
  "duplicate_of": ""
}