{
  "id": "OPM-2025-0004-9565",
  "title": "Comment from Fuck Trump",
  "category": "",
  "analysis": {
    "stance": "Against",
    "themes": [
      "Merit-based system concerns",
      "Due process/employee rights",
      "Politicization concerns"
    ],
    "key_quote": "The existing system, established in 1883, has worked for more than a century because it does, actually, work.",
    "rationale": "The comment opposes the proposed rule by defending the current merit-based system and expressing concerns about politicization and the potential for corruption in government appointments. The strong language and references to autocracy further indicate a clear opposition to the rule."
  },
  "occurrence_number": 0,
  "duplicate_of": ""
}