{
  "id": "OPM-2025-0004-16338",
  "title": "Comment from Anonymous",
  "category": "Agency",
  "analysis": {
    "stance": "Against",
    "themes": [
      "Due process/employee rights",
      "Politicization concerns",
      "Merit-based system concerns",
      "Institutional knowledge loss"
    ],
    "key_quote": "This rule threatens to inject dangerous levels of politicization into federal agencies that must remain impartial and rooted in science, evidence, and the public good.",
    "rationale": "The comment explicitly opposes the proposed rule, highlighting concerns about due process protections, politicization of federal agencies, and the importance of maintaining a merit-based system. The emphasis on the integrity of scientific research and the need for nonpartisan governance further supports the classification as 'Against'."
  },
  "occurrence_number": 0,
  "duplicate_of": ""
}