{
  "id": "OPM-2025-0004-2741",
  "title": "Comment from Helen Kinsella",
  "category": "Agency",
  "analysis": {
    "stance": "Against",
    "themes": [
      "Merit-based system concerns",
      "Politicization concerns"
    ],
    "key_quote": "Please do not gut/politicize or otherwise undermine career civil service.",
    "rationale": "The comment explicitly opposes the proposed rule by expressing concern about the politicization of the civil service and emphasizes the importance of nonpartisan service, which aligns with the themes of merit-based systems and politicization concerns."
  },
  "occurrence_number": 2,
  "duplicate_of": "OPM-2025-0004-1186,OPM-2025-0004-2741"
}