{
  "id": "OPM-2025-0004-1023",
  "title": "Comment from Jennifer Moore",
  "category": "Agency",
  "analysis": {
    "stance": "Against",
    "themes": [
      "Merit-based system concerns",
      "Politicization concerns"
    ],
    "key_quote": "The President is NOT a king. People hired by the federal government should be hired on ability, education and NOT who they support politically!",
    "rationale": "The comment opposes the proposed rule by emphasizing the importance of hiring based on merit rather than political affiliation, which aligns with concerns about politicization of the civil service."
  },
  "occurrence_number": 1,
  "duplicate_of": ""
}