{
  "id": "OPM-2025-0004-18872",
  "title": "Comment from Ann Tate",
  "category": "",
  "analysis": {
    "stance": "Against",
    "themes": [
      "Merit-based system concerns",
      "Due process/employee rights",
      "Politicization concerns"
    ],
    "key_quote": "To the extent that executive orders arguably contradict guidance and policy set forth by the Constitution and/or Congress, reclassifying program officials will leave them vulnerable to termination for reasons other than the merit of their performance or non-partisan execution of their duty.",
    "rationale": "The comment opposes the proposed rule by emphasizing the importance of merit-based performance and the risks of politicization, indicating that reclassification could undermine the integrity of program officials' roles."
  },
  "occurrence_number": 0,
  "duplicate_of": ""
}