{
  "id": "OPM-2025-0004-7671",
  "title": "Comment from Anonymous",
  "category": "Citizen",
  "analysis": {
    "stance": "Against",
    "themes": [
      "Merit-based system concerns",
      "Due process/employee rights",
      "Politicization concerns"
    ],
    "key_quote": "This policy change would be a serious mistake. This is a solution to a problem that doesn't really exist. It's meant to thwart opposition to the current president and employee only those who will agree with his orders. This is simply unconstitutional.",
    "rationale": "The comment explicitly opposes the proposed rule, highlighting concerns about its constitutionality and the potential for politicization of the civil service. It emphasizes the importance of communication and coordination among agencies, which aligns with merit-based system concerns."
  },
  "occurrence_number": 0,
  "duplicate_of": ""
}