{
  "id": "OPM-2025-0004-19115",
  "title": "Comment from Anonymous",
  "category": "",
  "analysis": {
    "stance": "Against",
    "themes": [
      "Merit-based system concerns",
      "Due process/employee rights",
      "Politicization concerns"
    ],
    "key_quote": "The proposed rule is a direct threat to American democracy and I oppose it as an American citizen with expertise in how political motivations can bias decision-making.",
    "rationale": "The comment explicitly opposes the proposed rule, highlighting concerns about politicization and the importance of a merit-based civil service. It emphasizes the need for an independent workforce free from political influence, which aligns with the themes of protecting civil service integrity."
  },
  "occurrence_number": 0,
  "duplicate_of": ""
}