{
  "id": "OPM-2025-0004-18256",
  "title": "Comment from Anonymous",
  "category": "Citizen",
  "analysis": {
    "stance": "Against",
    "themes": [
      "Due process/employee rights",
      "Politicization concerns"
    ],
    "key_quote": "I do not support this action because it is completely illegal, impairs due process, and does not allow the federal service to effectively do their jobs.",
    "rationale": "The comment explicitly opposes the proposed rule by stating it is illegal and impairs due process, which indicates a concern for employee rights and the integrity of the federal service."
  },
  "occurrence_number": 1,
  "duplicate_of": ""
}