{
  "id": "OPM-2025-0004-2946",
  "title": "Comment from Anonymous",
  "category": "",
  "analysis": {
    "stance": "Against",
    "themes": [
      "Due process/employee rights",
      "Politicization concerns"
    ],
    "key_quote": "This is possibly one of the worst things that could happen to government employees. Do not let this happen!",
    "rationale": "The comment expresses strong opposition to the proposed rule, indicating a concern for the rights of government employees and suggesting that it would negatively impact their protections, which aligns with themes of due process and politicization."
  },
  "occurrence_number": 1,
  "duplicate_of": ""
}