{
  "id": "OPM-2025-0004-3527",
  "title": "Comment from Emily Burgess",
  "category": "Agency",
  "analysis": {
    "stance": "Against",
    "themes": [
      "Due process/employee rights",
      "Politicization concerns"
    ],
    "key_quote": "I strongly oppose this rule change.",
    "rationale": "The comment explicitly states opposition to the rule change and highlights concerns about the removal of checks and balances, which aligns with themes of due process and the potential for politicization of the civil service."
  },
  "occurrence_number": 1,
  "duplicate_of": ""
}