{
  "id": "OPM-2025-0004-2082",
  "title": "Comment from Anonymous",
  "category": "Agency",
  "analysis": {
    "stance": "Against",
    "themes": [
      "Politicization concerns"
    ],
    "key_quote": "More overreach creating a kingdom where there was once a shining democracy.",
    "rationale": "The comment expresses strong opposition to the proposed rule by framing it as an overreach that undermines democratic principles, indicating concerns about politicization and the integrity of governance."
  },
  "occurrence_number": 1,
  "duplicate_of": ""
}