{
  "id": "OPM-2025-0004-21451",
  "title": "Comment from Anonymous",
  "category": "Citizen",
  "analysis": {
    "stance": "Against",
    "themes": [
      "Merit-based system concerns",
      "Due process/employee rights",
      "Politicization concerns"
    ],
    "key_quote": "This rule, by making it easier to dismiss experienced professionals without real justification, threatens to inject partisan politics right into the heart of our civil service.",
    "rationale": "The comment explicitly opposes the proposed rule, emphasizing the importance of a merit-based system and the dangers of politicization in the civil service, which aligns with concerns about integrity and due process."
  },
  "occurrence_number": 0,
  "duplicate_of": ""
}