{
  "id": "OPM-2025-0004-1007",
  "title": "Comment from Anonymous",
  "category": "Agency",
  "analysis": {
    "stance": "Against",
    "themes": [
      "Politicization concerns"
    ],
    "key_quote": "Classifying more civil servants as \u201cSchedule F\u201d will result in a larger population of the federal workforce laboring under the threat of potential political retaliation rather than laboring for the people.",
    "rationale": "The comment expresses concern that the proposed rule will politicize the civil service, leading to federal employees being influenced by political pressures rather than serving the public, which aligns with opposition to the rule."
  },
  "occurrence_number": 0,
  "duplicate_of": ""
}