{
  "id": "OPM-2025-0004-2463",
  "title": "Comment from Elizabeth Smith",
  "category": "Agency",
  "analysis": {
    "stance": "Against",
    "themes": [
      "Merit-based system concerns",
      "Due process/employee rights",
      "Politicization concerns",
      "Institutional knowledge loss"
    ],
    "key_quote": "I strongly oppose this proposed regulation which would simplify the firing the civil servants who don\u2019t comply with the president\u2019s policy agenda.",
    "rationale": "The comment explicitly opposes the proposed regulation, highlighting concerns about politicization, the undermining of established expertise, and the potential for retribution against civil servants, which aligns with themes opposing the rule."
  },
  "occurrence_number": 0,
  "duplicate_of": ""
}