{
  "id": "OPM-2025-0004-3963",
  "title": "Comment from Caty Frost",
  "category": "Agency",
  "analysis": {
    "stance": "Against",
    "themes": [
      "Merit-based system concerns",
      "Due process/employee rights",
      "Politicization concerns"
    ],
    "key_quote": "The implementation of this regulation would allow the Executive Branch to fire whomever they like and for whatever reason; under the current administration, this can and will be abused in order to fill these positions with loyalists.",
    "rationale": "The comment explicitly opposes the proposed rule by emphasizing the importance of merit-based hiring and the potential for politicization and abuse of power, which aligns with concerns about due process and employee rights."
  },
  "occurrence_number": 0,
  "duplicate_of": ""
}