{
  "id": "OPM-2025-0004-18843",
  "title": "Comment from Alex Buerkle",
  "category": "Agency",
  "analysis": {
    "stance": "Against",
    "themes": [
      "Politicization concerns",
      "Scientific integrity"
    ],
    "key_quote": "This new rule does not address a genuine problem and would result in interference in scientific decision making.",
    "rationale": "The comment opposes the rule by highlighting concerns about interference in scientific decision-making, which aligns with fears of politicization and undermines the integrity of scientific institutions."
  },
  "occurrence_number": 1,
  "duplicate_of": ""
}