{
  "id": "OPM-2025-0004-10591",
  "title": "Comment from Anonymous",
  "category": "Agency",
  "analysis": {
    "stance": "Against",
    "themes": [
      "Merit-based system concerns",
      "Due process/employee rights",
      "Politicization concerns"
    ],
    "key_quote": "Civil servants need to be protected from political influence and control over their jobs.",
    "rationale": "The comment expresses strong opposition to political influence in federal employment, emphasizing the need for merit-based systems and protections against retaliation, which aligns with concerns about politicization and employee rights."
  },
  "occurrence_number": 0,
  "duplicate_of": ""
}