{
  "id": "OPM-2025-0004-7375",
  "title": "Comment from Anonymous",
  "category": "Citizen",
  "analysis": {
    "stance": "Neutral/Unclear",
    "themes": [],
    "key_quote": "If you guys want to destroy the federal workforce then just do it already.",
    "rationale": "The comment expresses frustration with the proposed regulations but does not explicitly support or oppose the rule. It lacks clear themes related to civil service protections or politicization, making it ambiguous."
  },
  "occurrence_number": 1,
  "duplicate_of": ""
}