{
  "id": "OPM-2025-0004-8755",
  "title": "Comment from Anonymous",
  "category": "",
  "analysis": {
    "stance": "Against",
    "themes": [
      "Politicization concerns"
    ],
    "key_quote": "These jobs MUST remain non-partisan.",
    "rationale": "The comment explicitly states the necessity for jobs to remain non-partisan, which indicates a concern about the potential politicization of civil service positions. This aligns with opposition to the proposed rule."
  },
  "occurrence_number": 1,
  "duplicate_of": ""
}