{
  "id": "OPM-2025-0004-7565",
  "title": "Comment from Anonymous",
  "category": "Citizen",
  "analysis": {
    "stance": "Against",
    "themes": [
      "Due process/employee rights",
      "Politicization concerns"
    ],
    "key_quote": "This new approach and Schedule F are antithetical to the core belief of the United States and should not be pursued further.",
    "rationale": "The comment explicitly opposes Schedule F, emphasizing the need for oversight and the dangers of politicization in federal employment, which aligns with concerns about due process and employee rights."
  },
  "occurrence_number": 1,
  "duplicate_of": ""
}