{
  "id": "OPM-2025-0004-3742",
  "title": "Comment from Anonymous",
  "category": "Agency",
  "analysis": {
    "stance": "Against",
    "themes": [
      "Politicization concerns",
      "Due process/employee rights"
    ],
    "key_quote": "I oppose the new rule that would reclassify federal workers, making it easier to fire them for political reasons.",
    "rationale": "The comment explicitly opposes the rule and emphasizes the importance of non-partisan employees, indicating concerns about politicization and the potential for political influence in federal employment."
  },
  "occurrence_number": 1,
  "duplicate_of": ""
}