{
  "id": "OPM-2025-0004-1253",
  "title": "Comment from Anonymous",
  "category": "Agency",
  "analysis": {
    "stance": "Against",
    "themes": [
      "Merit-based system concerns",
      "Due process/employee rights",
      "Politicization concerns"
    ],
    "key_quote": "The bottom line is that Schedule F would represent an unprecedented increase in politicizing the federal workforce, which would predictably undermine performance and accountability in the federal government, as well as democratic values such as transparency and the rule of law.",
    "rationale": "The comment explicitly opposes the Schedule F rule by highlighting its potential to politicize the federal workforce and undermine merit-based protections, indicating a strong stance against the proposed rule."
  },
  "occurrence_number": 0,
  "duplicate_of": ""
}