{
  "id": "OPM-2025-0004-10107",
  "title": "Comment from Connie Montgomery",
  "category": "Agency",
  "analysis": {
    "stance": "Neutral/Unclear",
    "themes": [],
    "key_quote": "I am against anything that the Republicans propose because it\u2019s probably wrong and by the way, there is no deep state.",
    "rationale": "The comment primarily expresses personal political views and concerns about the current political climate without directly addressing the proposed rule or civil service themes. Therefore, it is classified as Neutral/Unclear."
  },
  "occurrence_number": 0,
  "duplicate_of": ""
}