{
  "id": "OPM-2025-0004-10582",
  "title": "Comment from Anonymous Anonymous",
  "category": "Agency",
  "analysis": {
    "stance": "Against",
    "themes": [
      "Politicization concerns"
    ],
    "key_quote": "Civil Servants should not be appointed to appease a particular political party.",
    "rationale": "The comment expresses strong opposition to the politicization of civil service, emphasizing that civil servants should remain loyal to the citizens rather than political parties, which aligns with concerns about the integrity of the civil service system."
  },
  "occurrence_number": 1,
  "duplicate_of": ""
}