{
  "id": "OPM-2025-0004-5642",
  "title": "Comment from thomas bartholomew",
  "category": "Citizen",
  "analysis": {
    "stance": "Against",
    "themes": [
      "Merit-based system concerns",
      "Due process/employee rights",
      "Politicization concerns"
    ],
    "key_quote": "A government that is run instead based on a system of loyalty to one political figure is at risk from breaking those constitutional requirements.",
    "rationale": "The comment strongly opposes the proposed rule by emphasizing the importance of a nonpartisan civil service and the dangers of politicization, which aligns with concerns about constitutional integrity and merit-based governance."
  },
  "occurrence_number": 0,
  "duplicate_of": ""
}