{
  "id": "OPM-2025-0004-9471",
  "title": "Comment from Katie Noonan",
  "category": "Citizen",
  "analysis": {
    "stance": "Against",
    "themes": [
      "Politicization concerns"
    ],
    "key_quote": "Please, Stop politicizing public service.",
    "rationale": "The comment explicitly opposes the politicization of public service, indicating a concern about the current administration's influence, which aligns with the themes of nonpartisan governance and integrity."
  },
  "occurrence_number": 1,
  "duplicate_of": ""
}