{
  "id": "OPM-2025-0004-20909",
  "title": "Comment from Anonymous",
  "category": "Agency",
  "analysis": {
    "stance": "Against",
    "themes": [
      "Politicization concerns"
    ],
    "key_quote": "Politicizing the civil government is dangerous and undemocratic.",
    "rationale": "The comment explicitly opposes the proposed rule by highlighting the dangers of politicizing civil service, indicating a concern for democratic principles and the integrity of public service."
  },
  "occurrence_number": 1,
  "duplicate_of": ""
}