{
  "id": "OPM-2025-0004-11527",
  "title": "Comment from Carol Long Long",
  "category": "Citizen",
  "analysis": {
    "stance": "Against",
    "themes": [
      "Politicization concerns"
    ],
    "key_quote": "THE RIGHT TO A NON-PARTISAN GOVERNMENT ADMINISTRATION IS VIOLATED BY THIS PLACING GOVERNMENT POSITIONS UNDER THE CONTROL OF ELECTED OFFICIALS.",
    "rationale": "The comment explicitly opposes the proposed rule by emphasizing the violation of non-partisan governance, which aligns with concerns about politicization of civil service."
  },
  "occurrence_number": 1,
  "duplicate_of": ""
}