{
  "id": "OPM-2025-0004-5668",
  "title": "Comment from Anonymous",
  "category": "Agency",
  "analysis": {
    "stance": "Against",
    "themes": [
      "Merit-based system concerns",
      "Politicization concerns"
    ],
    "key_quote": "We need to choose federal employees based on merit apart from political affiliation.",
    "rationale": "The comment opposes the proposed rule by emphasizing the importance of a merit-based system and expressing concerns about politicization in federal employment."
  },
  "occurrence_number": 1,
  "duplicate_of": ""
}