{
  "id": "OPM-2025-0004-1256",
  "title": "Comment from Anonymous",
  "category": "Citizen",
  "analysis": {
    "stance": "Against",
    "themes": [
      "Merit-based system concerns",
      "Due process/employee rights",
      "Politicization concerns",
      "Institutional knowledge loss"
    ],
    "key_quote": "This policy, in allowing for termination without cause, would lead to a critical loss in institutional memory and developed expertise and would cause unpredictability and lack of confidence in the people who interact with each agency.",
    "rationale": "The comment explicitly opposes the proposed rule, highlighting concerns about due process, the loss of institutional knowledge, and the potential for politicization of the civil service. It emphasizes the importance of existing merit-based systems for addressing performance issues."
  },
  "occurrence_number": 0,
  "duplicate_of": ""
}