{
  "id": "OPM-2025-0004-0456",
  "title": "Comment from A P",
  "category": "Agency",
  "analysis": {
    "stance": "Against",
    "themes": [
      "Merit-based system concerns",
      "Due process/employee rights",
      "Politicization concerns"
    ],
    "key_quote": "This is not in the interest of the American people. Rules and procedures are in place for terminating poor performing civil servants that ensure transparency and accountability of the agencies and supervisors.",
    "rationale": "The comment opposes the proposed rule by emphasizing the importance of existing procedures for accountability and transparency in managing poor performance, while also expressing concerns about the politicization of civil service roles."
  },
  "occurrence_number": 0,
  "duplicate_of": ""
}