{
  "id": "OPM-2025-0004-1700",
  "title": "Comment from Anna Hermes",
  "category": "Agency",
  "analysis": {
    "stance": "Against",
    "themes": [
      "Merit-based system concerns",
      "Due process/employee rights",
      "Politicization concerns"
    ],
    "key_quote": "Federal workers serve the public, not political leaders.",
    "rationale": "The comment explicitly opposes the rule by emphasizing the nonpartisan nature of federal workers and the potential erosion of democracy, which aligns with concerns about politicization and the integrity of the civil service."
  },
  "occurrence_number": 0,
  "duplicate_of": ""
}