{
  "id": "OPM-2025-0004-9709",
  "title": "Comment from Mary Austin",
  "category": "Agency",
  "analysis": {
    "stance": "Against",
    "themes": [
      "Merit-based system concerns",
      "Due process/employee rights",
      "Politicization concerns"
    ],
    "key_quote": "Career civil servants are an invaluable resource. Let's have more of them, not fewer.",
    "rationale": "The comment opposes the proposed rule by emphasizing the value of career civil servants and expressing concerns about the current administration's accountability and competence, which aligns with themes of merit-based systems and politicization."
  },
  "occurrence_number": 0,
  "duplicate_of": ""
}