{
  "id": "OPM-2025-0004-18265",
  "title": "Comment from Anonymous",
  "category": "Citizen",
  "analysis": {
    "stance": "Against",
    "themes": [
      "Politicization concerns"
    ],
    "key_quote": "I believe it is unsafe to politicize policy or potential policy making roles.",
    "rationale": "The comment expresses concern about the politicization of federal roles, emphasizing the importance of constitutional duty, which aligns with opposition to the proposed rule."
  },
  "occurrence_number": 1,
  "duplicate_of": ""
}