{
  "id": "OPM-2025-0004-21458",
  "title": "Comment from Anonymous",
  "category": "",
  "analysis": {
    "stance": "Against",
    "themes": [
      "Merit-based system concerns",
      "Due process/employee rights",
      "Politicization concerns",
      "Institutional knowledge loss"
    ],
    "key_quote": "This policy would make it easier for the administration to keep firing people and shutting down agencies and programs like the Peace Corps and Fulbright Program that have benefited thousands of Americans and protected the country by creating goodwill toward it around the world.",
    "rationale": "The comment explicitly opposes the proposed rule, highlighting concerns about the loss of institutional knowledge and the potential for increased politicization of the civil service, which undermines the merit-based system and employee rights."
  },
  "occurrence_number": 0,
  "duplicate_of": ""
}