{
  "id": "OPM-2025-0004-12351",
  "title": "Comment from Susan Spilecki",
  "category": "Agency",
  "analysis": {
    "stance": "Against",
    "themes": [
      "Politicization concerns"
    ],
    "key_quote": "Civil servants should be allowed to remain as nonpartisan experts, rather than loyalists to Trump\u2019s political agenda.",
    "rationale": "The comment explicitly opposes the proposed rule by emphasizing the importance of nonpartisan civil service and rejecting the idea of civil servants becoming loyalists to a political agenda, which indicates a concern about politicization."
  },
  "occurrence_number": 1,
  "duplicate_of": ""
}