{
  "id": "OPM-2025-0004-17398",
  "title": "Comment from Anonymous",
  "category": "",
  "analysis": {
    "stance": "Against",
    "themes": [
      "Politicization concerns"
    ],
    "key_quote": "Civil servants should remain non-partisan and professional. They should be not politically appointed through favoritism.",
    "rationale": "The comment explicitly opposes the proposed rule by emphasizing the importance of non-partisanship and professionalism in civil service, which aligns with concerns about politicization."
  },
  "occurrence_number": 1,
  "duplicate_of": ""
}