{
  "id": "OPM-2025-0004-1976",
  "title": "Comment from Olivia Hardin",
  "category": "Agency",
  "analysis": {
    "stance": "Against",
    "themes": [
      "Merit-based system concerns",
      "Due process/employee rights",
      "Politicization concerns"
    ],
    "key_quote": "Please don't create a rule that will make it easier to fire public servants without cause.",
    "rationale": "The comment expresses concern about the proposed rule's potential to undermine the role of career federal workers and emphasizes the importance of due process and protections for public servants, indicating opposition to the rule."
  },
  "occurrence_number": 0,
  "duplicate_of": ""
}