{
  "id": "OPM-2025-0004-11616",
  "title": "Comment from Pamela Trinch",
  "category": "",
  "analysis": {
    "stance": "Against",
    "themes": [
      "Merit-based system concerns",
      "Due process/employee rights",
      "Politicization concerns"
    ],
    "key_quote": "Implementation of Schedule P/C at SSA would further deteriorate services and threaten the mission of the agency.",
    "rationale": "The comment explicitly opposes the proposed rule, highlighting concerns about the politicization of civil service and the potential negative impact on service quality and employee rights."
  },
  "occurrence_number": 0,
  "duplicate_of": ""
}