{
  "id": "OPM-2025-0004-0397",
  "title": "Comment from James Lederer",
  "category": "Agency",
  "analysis": {
    "stance": "Against",
    "themes": [
      "Politicization concerns",
      "Institutional knowledge loss"
    ],
    "key_quote": "This politicization of previously apolitical career civil service positions is wrong, and will fill the civil service with \u201cyes-men\u201d while replacing experienced employees and losing their expertise.",
    "rationale": "The comment explicitly opposes the proposed rule by highlighting concerns about the politicization of civil service positions and the potential loss of experienced employees, which aligns with the themes of politicization and institutional knowledge loss."
  },
  "occurrence_number": 1,
  "duplicate_of": ""
}