{
  "id": "OPM-2025-0004-10412",
  "title": "Comment from Molly Hauck",
  "category": "Citizen",
  "analysis": {
    "stance": "Against",
    "themes": [
      "Merit-based system concerns",
      "Due process/employee rights",
      "Politicization concerns"
    ],
    "key_quote": "President Trump just took the next step toward giving himself the power to bypass the guardrails that are supposed to keep our basic government services free of political influence.",
    "rationale": "The comment strongly opposes the proposed rule by highlighting concerns about politicization of the federal workforce and the erosion of due process rights for civil servants, indicating a clear stance against the rule."
  },
  "occurrence_number": 0,
  "duplicate_of": ""
}