{
  "id": "OPM-2025-0004-1597",
  "title": "Comment from briggid larson",
  "category": "",
  "analysis": {
    "stance": "Against",
    "themes": [
      "Due process/employee rights",
      "Politicization concerns"
    ],
    "key_quote": "Leave our federal workers to work stop with the job cutting the taking away of any protections.",
    "rationale": "The comment opposes the proposed rule by expressing concern over the removal of protections for federal workers, indicating a desire to maintain employee rights. Additionally, the reference to 'loyal trump sicccophants' suggests a concern about politicization within the civil service."
  },
  "occurrence_number": 1,
  "duplicate_of": ""
}