{
  "id": "OPM-2025-0004-12601",
  "title": "Comment from Anonymous",
  "category": "Citizen",
  "analysis": {
    "stance": "Neutral/Unclear",
    "themes": [],
    "key_quote": "What are the costs associated with a manager (who opposes the President's priorities) removing a subordinate (who supports the President's priorities) under Schedule Policy/Career?",
    "rationale": "The comment primarily seeks information regarding potential scenarios and implications of the proposed rule without expressing a clear stance for or against it."
  },
  "occurrence_number": 1,
  "duplicate_of": ""
}