{
  "id": "OPM-2025-0004-9411",
  "title": "Comment from Pamela Morgan",
  "category": "Agency",
  "analysis": {
    "stance": "Against",
    "themes": [
      "Politicization concerns"
    ],
    "key_quote": "This is a terrible idea. Don't make rules designed to break our government and/or torture our civil servants.",
    "rationale": "The comment explicitly opposes the proposed rule by expressing strong disapproval and concern for the impact on civil servants, indicating a belief that it would harm the integrity of government operations."
  },
  "occurrence_number": 1,
  "duplicate_of": ""
}