{
  "id": "OPM-2025-0004-0694",
  "title": "Comment from Nick  Fitzkee",
  "category": "Agency",
  "analysis": {
    "stance": "Against",
    "themes": [
      "Politicization concerns",
      "Scientific integrity"
    ],
    "key_quote": "This is a horrible idea that will totally upend academic freedom in the biomedical sciences at federal research institutions.",
    "rationale": "The comment expresses strong opposition to the proposed rule by highlighting concerns about politicization and its negative impact on academic freedom and public service in the biomedical sciences."
  },
  "occurrence_number": 1,
  "duplicate_of": ""
}